pyjamas_core/__init__.py
pyjamas_core/agent.py
pyjamas_core/controller.py
pyjamas_core/supermodel.py
pyjamas_core/util.py
pyjamas_core-0.1.1.dist-info/LICENSE
pyjamas_core-0.1.1.dist-info/METADATA
pyjamas_core-0.1.1.dist-info/WHEEL
pyjamas_core-0.1.1.dist-info/top_level.txt
pyjamas_core-0.1.1.dist-info/RECORD
